derivationtree/__init__.py
derivationtree/dtree.py
derivationtree-0.4.3.dist-info/METADATA
derivationtree-0.4.3.dist-info/WHEEL
derivationtree-0.4.3.dist-info/top_level.txt
derivationtree-0.4.3.dist-info/RECORD
