Metadata-Version: 2.1
Name: derivationtree
Version: 0.4.3
Summary: An efficient derivation tree implementation for grammar fuzzing and other applications.
Home-page: https://github.com/rindPHI/derivationtree
Author: Dominic Steinhoefel
Author-email: Dominic Steinhoefel <dominic.steinhoefel@cispa.de>
Project-URL: Homepage, https://github.com/rindPHI/derivationtree/
Project-URL: Bug Tracker, https://github.com/rindPHI/derivationtree/issues
Classifier: Intended Audience :: Science/Research
Classifier: License :: OSI Approved :: GNU General Public License v3 (GPLv3)
Classifier: Programming Language :: Python :: 3.10
Classifier: Operating System :: OS Independent
Classifier: Topic :: Scientific/Engineering
Classifier: Topic :: Security
Classifier: Topic :: Software Development :: Testing
Requires-Python: >=3.10
Requires-Dist: datrie (>=0.8.2)
Requires-Dist: grammar-graph (>=0.1.14)
Requires-Dist: graphviz (>=0.20.1)
Provides-Extra: dev
Requires-Dist: black (>=22.10.0) ; extra == 'dev'
Requires-Dist: build (>=0.9.0) ; extra == 'dev'
Requires-Dist: flake8 (>=6.0.0) ; extra == 'dev'
Requires-Dist: twine (>=4.0.2) ; extra == 'dev'
Provides-Extra: test
Requires-Dist: coverage (>=6.5.0) ; extra == 'test'
Requires-Dist: pytest (>=7.2.0) ; extra == 'test'
